easy_gateway/cli.py
easy_gateway/config.py
easy_gateway/gateway/__init__.py
easy_gateway/gateway/core.py
easy_gateway/gateway/handler.py
easy_gateway/middleware/__init__.py
easy_gateway/middleware/base.py
easy_gateway/middleware/logging_middleware.py
easy_gateway/middleware/rate_limit_middleware.py
easy_gateway/router/__init__.py
easy_gateway/router/router.py
easy_gateway-0.1.6.dist-info/LICENSE
easy_gateway-0.1.6.dist-info/METADATA
easy_gateway-0.1.6.dist-info/WHEEL
easy_gateway-0.1.6.dist-info/entry_points.txt
easy_gateway-0.1.6.dist-info/top_level.txt
easy_gateway-0.1.6.dist-info/RECORD
